kebihelp/__init__.py
kebihelp/config.py
kebihelp/gui.py
kebihelp/main.py
kebihelp/parsers.py
kebihelp-0.1.2.dist-info/LICENSE
kebihelp-0.1.2.dist-info/METADATA
kebihelp-0.1.2.dist-info/WHEEL
kebihelp-0.1.2.dist-info/entry_points.txt
kebihelp-0.1.2.dist-info/top_level.txt
kebihelp-0.1.2.dist-info/RECORD
