Metadata-Version: 2.1
Name: kebihelp
Version: 0.1.2
Summary: A Linux universal keybindings helper written in Python/QT5
Author-email: Julien Pro <contact@julienpro.com>
Project-URL: Homepage, https://github.com/juienpro/kebihelp
Project-URL: Issues, https://github.com/juienpro/kebihelp/issues
Classifier: Intended Audience :: Developers
Classifier: License :: OSI Approved :: MIT License
Classifier: Programming Language :: Python :: 3
Classifier: Programming Language :: Python :: 3.11
Classifier: Operating System :: POSIX :: Linux
Classifier: Topic :: System :: Operating System
Classifier: Topic :: System :: Systems Administration
Classifier: Topic :: Desktop Environment
Requires-Python: >=3.11
License-File: LICENSE
Requires-Dist: prettytable >=3.10.0
Requires-Dist: PyQt5 >=5.15.10
Requires-Dist: PyQt5-sip >=12.13.0
